{
  "A": [
    { "titel": "Week 1", "inhoud": [
      { "datum": "2019-01-02", "omschrijving": "4 x 6 min 80%, 2 min rust 70%", "locatie": "Zilvermeer"},
      { "datum": "2019-01-05", "omschrijving": "6 x 4 min 85%, 1 min 70%", "locatie": "rondje voetbalveld"},
      { "titel": "eigen 3e training", "datum": "2019-01-07", "omschrijving": "Duurloop 50 min 75%"}]},



    { "titel": "Week 2", "inhoud": [
      { "datum": "2019-01-09", "omschrijving": "3 x brug op en af van Goningerweg tot Bedumerweg. 85% op, 70% af.", "locatie": "Noordzeebrug"},
      { "datum": "2019-01-12", "omschrijving": "3 x 10 min 85%, 4 min rust 70%", "locatie": "Richting Paddepoelsterbrug"},
      { "titel": "eigen 3e training", "datum": "2019-01-14", "omschrijving": "Duurloop 50 min 75%"}]}
  ],

  "B": [
    { "titel": "Week 1", "inhoud": [
      { "datum": "2019-01-02", "omschrijving": "6 x 6 min 80%, 2 min rust 70%", "locatie": "Zilvermeer"},
      { "datum": "2019-01-05", "omschrijving": "8 x 4 min 85%, 1 min 70%", "locatie": "4 mijl parcours geheel"},
      { "titel": "eigen 3e training", "datum": "2019-01-07", "omschrijving": "Duurloop 70 min 75%, laatste 10 min 85%"}]},



    { "titel": "Week 2", "inhoud": [
      { "datum": "2019-01-09", "omschrijving": "4 x brug op en af van Goningerweg tot Bedumerweg. 85% op, 70% af.", "locatie": "Noordzeebrug"},
      { "datum": "2019-01-12", "omschrijving": "3 x 12 min 85%, 4 min rust 70%", "locatie": "Richting Paddepoelsterbrug"},
      { "titel": "eigen 3e training", "datum": "2019-01-14", "omschrijving": "Duurloop 75 min 75%, laatste 10 min 85%"}]}
  ],

  "C": [
    { "titel": "Week 1", "inhoud": [
      { "datum": "2019-01-02", "omschrijving": "8 x 6 min 80%, 2 min rust 70%", "locatie": "Zilvermeer"},
      { "datum": "2019-01-05", "omschrijving": "10 x 4 min 85%, 1 min 70%", "locatie": "4 mijl parcours met Beijumerbos"},
      { "titel": "eigen 3e training", "datum": "2019-01-07", "omschrijving": "Duurloop 90 min 75%, laatste 10 min 85%"}]},



    { "titel": "Week 2", "inhoud": [
      { "datum": "2019-01-09", "omschrijving": "5 x brug op en af van Goningerweg tot Bedumerweg. 85% op, 70% af.", "locatie": "Noordzeebrug"},
      { "datum": "2019-01-12", "omschrijving": "3 x 15 min 85%, 4 min rust 70%", "locatie": "Richting Paddepoelsterbrug"},
      { "titel": "eigen 3e training", "datum": "2019-01-14", "omschrijving": "Duurloop 100 min 75%, laatste 10 min 85%"}]}
  ]
}
